setup.py
timenlpy/LunarSolarConverter.py
timenlpy/RangeTimeEnum.py
timenlpy/StringPreHandler.py
timenlpy/Test.py
timenlpy/TimeNormalizer.py
timenlpy/TimePoint.py
timenlpy/TimeUnit.py
timenlpy/__init__.py
timenlpy.egg-info/PKG-INFO
timenlpy.egg-info/SOURCES.txt
timenlpy.egg-info/dependency_links.txt
timenlpy.egg-info/not-zip-safe
timenlpy.egg-info/requires.txt
timenlpy.egg-info/top_level.txt